kupper_hafner/__init__.py
kupper_hafner/kupper_hafner.py
tests/__init__.py
tests/test_kupper_hafner.py
kupper_hafner-0.1.0.dist-info/LICENSE
kupper_hafner-0.1.0.dist-info/METADATA
kupper_hafner-0.1.0.dist-info/WHEEL
kupper_hafner-0.1.0.dist-info/top_level.txt
kupper_hafner-0.1.0.dist-info/RECORD
