Metadata-Version: 2.1
Name: kupper_hafner
Version: 0.1.0
Summary: Kupper-Hafner inter-rater agreement calculation library
Home-page: http://github.com/nmalkin/kupper_hafner
Author: nmalkin
License: BSD
Platform: UNKNOWN
Requires-Python: >=2.7
License-File: LICENSE
